ccvtools/__init__.py
ccvtools/__main__.py
ccvtools/ccv.py
ccvtools/rawio/CamCommandoFormat.py
ccvtools/rawio/Filters.py
ccvtools/rawio/__init__.py
ccvtools/rawio/ccv_header.py
ccvtools/rawio/ccvideo.py
ccvtools/rawio/utils.py
bbo_ccvtools-1.2.6.dist-info/METADATA
bbo_ccvtools-1.2.6.dist-info/WHEEL
bbo_ccvtools-1.2.6.dist-info/licenses/LICENSE
bbo_ccvtools-1.2.6.dist-info/RECORD
