Metadata-Version: 2.4
Name: bbo-ccvtools
Version: 1.2.6
Summary: Work with BBO CCV files
Project-URL: Homepage, https://github.com/bbo-lab/ccvtools
Author-email: "BBO-lab @ caesar" <kay-michael.voit@caesar.de>
License: BSD-3-Clause
License-File: LICENSE
Classifier: License :: OSI Approved :: BSD License
Classifier: Programming Language :: Python :: 3
Classifier: Programming Language :: Python :: 3.6
Classifier: Programming Language :: Python :: 3.7
Classifier: Programming Language :: Python :: 3.8
Requires-Dist: construct
Requires-Dist: imageio
Requires-Dist: imageio-ffmpeg
Requires-Dist: mutagen
Requires-Dist: numpy
Requires-Dist: pyjson
